MANIFEST.in
README.txt
setup.cfg
setup.py
docs/HISTORY.txt
raptus/__init__.py
raptus.notification.egg-info/PKG-INFO
raptus.notification.egg-info/SOURCES.txt
raptus.notification.egg-info/dependency_links.txt
raptus.notification.egg-info/entry_points.txt
raptus.notification.egg-info/namespace_packages.txt
raptus.notification.egg-info/not-zip-safe
raptus.notification.egg-info/requires.txt
raptus.notification.egg-info/top_level.txt
raptus/notification/__init__.py
raptus/notification/browser.py
raptus/notification/configure.zcml
raptus/notification/interfaces.py
raptus/notification/notification.css
raptus/notification/notification.js
raptus/notification/notification.py
raptus/notification/notifications.pt
raptus/notification/portlet.pt
raptus/notification/portlet.py
raptus/notification/setuphandlers.py
raptus/notification/Extensions/Install.py
raptus/notification/Extensions/__init__.py
raptus/notification/profiles/default/cssregistry.xml
raptus/notification/profiles/default/jsregistry.xml
raptus/notification/profiles/default/metadata.xml
raptus/notification/profiles/default/portlets.xml
raptus/notification/profiles/uninstall/cssregistry.xml
raptus/notification/profiles/uninstall/jsregistry.xml
raptus/notification/profiles/uninstall/raptus.notification.uninstall.txt