Metadata-Version: 1.0
Name: raptus.notification
Version: 1.0a1
Summary: Provides a generic way to send notifications to users in plone
Home-page: http://raptus.com
Author: Raptus AG
Author-email: dev@raptus.com
License: GPL
Platform: UNKNOWN
Classifier: Programming Language :: Python
Classifier: Topic :: Software Development :: Libraries :: Python Modules
